robodyno/__init__.py
robodyno/components/__init__.py
robodyno/components/can_bus/__init__.py
robodyno/components/can_bus/adaptive_gripper.py
robodyno/components/can_bus/battery.py
robodyno/components/can_bus/can_bus_device.py
robodyno/components/can_bus/cliff_sensor.py
robodyno/components/can_bus/gps_sensor.py
robodyno/components/can_bus/impact_sensor.py
robodyno/components/can_bus/imu_sensor.py
robodyno/components/can_bus/led_driver.py
robodyno/components/can_bus/magnetic_sensor.py
robodyno/components/can_bus/mi_motor.py
robodyno/components/can_bus/motor.py
robodyno/components/can_bus/proximity_sensor.py
robodyno/components/can_bus/pwm_driver.py
robodyno/components/can_bus/slider_module.py
robodyno/components/can_bus/stepper_driver.py
robodyno/components/can_bus/ultrasonic_sensor.py
robodyno/components/can_bus/vacuum_gripper.py
robodyno/components/config/__init__.py
robodyno/components/config/model.py
robodyno/components/config/robottime_config.py
robodyno/components/webots/__init__.py
robodyno/components/webots/motor.py
robodyno/components/webots/slider_module.py
robodyno/components/webots/webots_device.py
robodyno/interfaces/__init__.py
robodyno/interfaces/can_bus.py
robodyno/interfaces/webots.py
robodyno/robots/__init__.py
robodyno/robots/four_dof_palletizing_robot/__init__.py
robodyno/robots/four_dof_palletizing_robot/four_dof_pallet_robot.py
robodyno/robots/four_dof_scara_robot/__init__.py
robodyno/robots/four_dof_scara_robot/four_dof_scara_robot.py
robodyno/robots/six_dof_collaborative_robot/__init__.py
robodyno/robots/six_dof_collaborative_robot/six_dof_collab_robot.py
robodyno/robots/three_dof_cartesian_robot/__init__.py
robodyno/robots/three_dof_cartesian_robot/three_dof_cartesian_robot.py
robodyno/robots/three_dof_delta_robot/__init__.py
robodyno/robots/three_dof_delta_robot/three_dof_delta_robot.py
robodyno/robots/three_dof_palletizing_robot/__init__.py
robodyno/robots/three_dof_palletizing_robot/three_dof_pallet_robot.py
robodyno-1.7.2.dist-info/LICENSE
robodyno-1.7.2.dist-info/METADATA
robodyno-1.7.2.dist-info/WHEEL
robodyno-1.7.2.dist-info/entry_points.txt
robodyno-1.7.2.dist-info/top_level.txt
robodyno-1.7.2.dist-info/RECORD
