Metadata-Version: 2.1
Name: robodyno
Version: 1.7.2
Summary: The Robodyno Robot SDK for Python 3
Home-page: http://101.42.250.169/
Author: song
Author-email: zhaosongy@126.com
Maintainer: robottime
Maintainer-email: lab@robottime.cn
License: Apache License, Version 2.0
Keywords: robodyno,robot,robot module
Classifier: License :: OSI Approved :: Apache Software License
Classifier: Operating System :: Microsoft :: Windows
Classifier: Operating System :: POSIX :: Linux
Classifier: Framework :: Robot Framework
Classifier: Intended Audience :: Developers
Classifier: Intended Audience :: Education
Classifier: Intended Audience :: Science/Research
Classifier: Programming Language :: Python :: 3 :: Only
Classifier: Programming Language :: Python :: 3.6
Classifier: Programming Language :: Python :: 3.7
Classifier: Programming Language :: Python :: 3.8
Classifier: Programming Language :: Python :: 3.9
Classifier: Programming Language :: Python :: 3.10
Classifier: Programming Language :: Python :: 3.11
Classifier: Programming Language :: Python :: 3.12
Classifier: Programming Language :: Python :: 3.13
Classifier: Programming Language :: Python :: 3.14
Requires-Python: >=3.6
License-File: LICENSE
Requires-Dist: numpy >=1.10.0
Requires-Dist: rich >=12.6.0
Requires-Dist: click >=7.1.2
Requires-Dist: python-can <4.0,>=3.2.0
Requires-Dist: importlib-metadata
Requires-Dist: setuptools <80.0
Requires-Dist: candle-bus ; sys_platform == "win32"
